azure/mgmt/agrifood/__init__.py
azure/mgmt/agrifood/_agri_food_mgmt_client.py
azure/mgmt/agrifood/_configuration.py
azure/mgmt/agrifood/_patch.py
azure/mgmt/agrifood/_serialization.py
azure/mgmt/agrifood/_vendor.py
azure/mgmt/agrifood/_version.py
azure/mgmt/agrifood/py.typed
azure/mgmt/agrifood/aio/__init__.py
azure/mgmt/agrifood/aio/_agri_food_mgmt_client.py
azure/mgmt/agrifood/aio/_configuration.py
azure/mgmt/agrifood/aio/_patch.py
azure/mgmt/agrifood/aio/operations/__init__.py
azure/mgmt/agrifood/aio/operations/_extensions_operations.py
azure/mgmt/agrifood/aio/operations/_farm_beats_extensions_operations.py
azure/mgmt/agrifood/aio/operations/_farm_beats_models_operations.py
azure/mgmt/agrifood/aio/operations/_locations_operations.py
azure/mgmt/agrifood/aio/operations/_operations.py
azure/mgmt/agrifood/aio/operations/_patch.py
azure/mgmt/agrifood/aio/operations/_private_endpoint_connections_operations.py
azure/mgmt/agrifood/aio/operations/_private_link_resources_operations.py
azure/mgmt/agrifood/aio/operations/_solutions_discoverability_operations.py
azure/mgmt/agrifood/aio/operations/_solutions_operations.py
azure/mgmt/agrifood/models/__init__.py
azure/mgmt/agrifood/models/_agri_food_mgmt_client_enums.py
azure/mgmt/agrifood/models/_models_py3.py
azure/mgmt/agrifood/models/_patch.py
azure/mgmt/agrifood/operations/__init__.py
azure/mgmt/agrifood/operations/_extensions_operations.py
azure/mgmt/agrifood/operations/_farm_beats_extensions_operations.py
azure/mgmt/agrifood/operations/_farm_beats_models_operations.py
azure/mgmt/agrifood/operations/_locations_operations.py
azure/mgmt/agrifood/operations/_operations.py
azure/mgmt/agrifood/operations/_patch.py
azure/mgmt/agrifood/operations/_private_endpoint_connections_operations.py
azure/mgmt/agrifood/operations/_private_link_resources_operations.py
azure/mgmt/agrifood/operations/_solutions_discoverability_operations.py
azure/mgmt/agrifood/operations/_solutions_operations.py
azure_mgmt_agrifood-1.0.0b3.dist-info/LICENSE
azure_mgmt_agrifood-1.0.0b3.dist-info/METADATA
azure_mgmt_agrifood-1.0.0b3.dist-info/WHEEL
azure_mgmt_agrifood-1.0.0b3.dist-info/top_level.txt
azure_mgmt_agrifood-1.0.0b3.dist-info/RECORD
